{
  "30743211": {
    "pages": [
      {
        "slots": [
          {
            "runeId": 5251,
            "runeSlotId": 1
          },
          {
            "runeId": 5245,
            "runeSlotId": 2
          },
          {
            "runeId": 5245,
            "runeSlotId": 3
          },
          {
            "runeId": 5245,
            "runeSlotId": 4
          },
          {
            "runeId": 5245,
            "runeSlotId": 5
          },
          {
            "runeId": 5245,
            "runeSlotId": 6
          },
          {
            "runeId": 5245,
            "runeSlotId": 7
          },
          {
            "runeId": 5245,
            "runeSlotId": 8
          },
          {
            "runeId": 5245,
            "runeSlotId": 9
          },
          {
            "runeId": 5317,
            "runeSlotId": 10
          },
          {
            "runeId": 5317,
            "runeSlotId": 11
          },
          {
            "runeId": 5317,
            "runeSlotId": 12
          },
          {
            "runeId": 5317,
            "runeSlotId": 13
          },
          {
            "runeId": 5317,
            "runeSlotId": 14
          },
          {
            "runeId": 5317,
            "runeSlotId": 15
          },
          {
            "runeId": 5317,
            "runeSlotId": 16
          },
          {
            "runeId": 5317,
            "runeSlotId": 17
          },
          {
            "runeId": 5317,
            "runeSlotId": 18
          },
          {
            "runeId": 5289,
            "runeSlotId": 19
          },
          {
            "runeId": 5289,
            "runeSlotId": 20
          },
          {
            "runeId": 5289,
            "runeSlotId": 21
          },
          {
            "runeId": 5289,
            "runeSlotId": 22
          },
          {
            "runeId": 5289,
            "runeSlotId": 23
          },
          {
            "runeId": 5289,
            "runeSlotId": 24
          },
          {
            "runeId": 5289,
            "runeSlotId": 25
          },
          {
            "runeId": 5289,
            "runeSlotId": 26
          },
          {
            "runeId": 5289,
            "runeSlotId": 27
          },
          {
            "runeId": 5335,
            "runeSlotId": 28
          },
          {
            "runeId": 5412,
            "runeSlotId": 29
          },
          {
            "runeId": 5412,
            "runeSlotId": 30
          }
        ],
        "current": false,
        "name": "ADC \/ Normal",
        "id": 27908064
      },
      {
        "slots": [
          {
            "runeId": 5251,
            "runeSlotId": 1
          },
          {
            "runeId": 5245,
            "runeSlotId": 2
          },
          {
            "runeId": 5245,
            "runeSlotId": 3
          },
          {
            "runeId": 5245,
            "runeSlotId": 4
          },
          {
            "runeId": 5245,
            "runeSlotId": 5
          },
          {
            "runeId": 5245,
            "runeSlotId": 6
          },
          {
            "runeId": 5245,
            "runeSlotId": 7
          },
          {
            "runeId": 5245,
            "runeSlotId": 8
          },
          {
            "runeId": 5245,
            "runeSlotId": 9
          },
          {
            "runeId": 5317,
            "runeSlotId": 10
          },
          {
            "runeId": 5317,
            "runeSlotId": 11
          },
          {
            "runeId": 5317,
            "runeSlotId": 12
          },
          {
            "runeId": 5317,
            "runeSlotId": 13
          },
          {
            "runeId": 5317,
            "runeSlotId": 14
          },
          {
            "runeId": 5317,
            "runeSlotId": 15
          },
          {
            "runeId": 5317,
            "runeSlotId": 16
          },
          {
            "runeId": 5317,
            "runeSlotId": 17
          },
          {
            "runeId": 5317,
            "runeSlotId": 18
          },
          {
            "runeId": 5289,
            "runeSlotId": 19
          },
          {
            "runeId": 5289,
            "runeSlotId": 20
          },
          {
            "runeId": 5289,
            "runeSlotId": 21
          },
          {
            "runeId": 5289,
            "runeSlotId": 22
          },
          {
            "runeId": 5289,
            "runeSlotId": 23
          },
          {
            "runeId": 5289,
            "runeSlotId": 24
          },
          {
            "runeId": 5289,
            "runeSlotId": 25
          },
          {
            "runeId": 5289,
            "runeSlotId": 26
          },
          {
            "runeId": 5289,
            "runeSlotId": 27
          },
          {
            "runeId": 5335,
            "runeSlotId": 28
          },
          {
            "runeId": 5412,
            "runeSlotId": 29
          },
          {
            "runeId": 5412,
            "runeSlotId": 30
          }
        ],
        "current": false,
        "name": "ADC \/ Mana",
        "id": 27908065
      },
      {
        "slots": [
          {
            "runeId": 5251,
            "runeSlotId": 1
          },
          {
            "runeId": 5245,
            "runeSlotId": 2
          },
          {
            "runeId": 5245,
            "runeSlotId": 3
          },
          {
            "runeId": 5245,
            "runeSlotId": 4
          },
          {
            "runeId": 5245,
            "runeSlotId": 5
          },
          {
            "runeId": 5245,
            "runeSlotId": 6
          },
          {
            "runeId": 5245,
            "runeSlotId": 7
          },
          {
            "runeId": 5245,
            "runeSlotId": 8
          },
          {
            "runeId": 5245,
            "runeSlotId": 9
          },
          {
            "runeId": 5317,
            "runeSlotId": 10
          },
          {
            "runeId": 5317,
            "runeSlotId": 11
          },
          {
            "runeId": 5317,
            "runeSlotId": 12
          },
          {
            "runeId": 5317,
            "runeSlotId": 13
          },
          {
            "runeId": 5317,
            "runeSlotId": 14
          },
          {
            "runeId": 5317,
            "runeSlotId": 15
          },
          {
            "runeId": 5317,
            "runeSlotId": 16
          },
          {
            "runeId": 5317,
            "runeSlotId": 17
          },
          {
            "runeId": 5317,
            "runeSlotId": 18
          },
          {
            "runeId": 5289,
            "runeSlotId": 19
          },
          {
            "runeId": 5289,
            "runeSlotId": 20
          },
          {
            "runeId": 5289,
            "runeSlotId": 21
          },
          {
            "runeId": 5289,
            "runeSlotId": 22
          },
          {
            "runeId": 5289,
            "runeSlotId": 23
          },
          {
            "runeId": 5289,
            "runeSlotId": 24
          },
          {
            "runeId": 5289,
            "runeSlotId": 25
          },
          {
            "runeId": 5289,
            "runeSlotId": 26
          },
          {
            "runeId": 5289,
            "runeSlotId": 27
          },
          {
            "runeId": 5335,
            "runeSlotId": 28
          },
          {
            "runeId": 5335,
            "runeSlotId": 29
          },
          {
            "runeId": 5335,
            "runeSlotId": 30
          }
        ],
        "current": false,
        "name": "AD Standard",
        "id": 31038297
      },
      {
        "slots": [
          {
            "runeId": 5251,
            "runeSlotId": 1
          },
          {
            "runeId": 5245,
            "runeSlotId": 2
          },
          {
            "runeId": 5245,
            "runeSlotId": 3
          },
          {
            "runeId": 5245,
            "runeSlotId": 4
          },
          {
            "runeId": 5245,
            "runeSlotId": 5
          },
          {
            "runeId": 5245,
            "runeSlotId": 6
          },
          {
            "runeId": 5245,
            "runeSlotId": 7
          },
          {
            "runeId": 5245,
            "runeSlotId": 8
          },
          {
            "runeId": 5245,
            "runeSlotId": 9
          },
          {
            "runeId": 5317,
            "runeSlotId": 10
          },
          {
            "runeId": 5317,
            "runeSlotId": 11
          },
          {
            "runeId": 5317,
            "runeSlotId": 12
          },
          {
            "runeId": 5317,
            "runeSlotId": 13
          },
          {
            "runeId": 5317,
            "runeSlotId": 14
          },
          {
            "runeId": 5317,
            "runeSlotId": 15
          },
          {
            "runeId": 5317,
            "runeSlotId": 16
          },
          {
            "runeId": 5317,
            "runeSlotId": 17
          },
          {
            "runeId": 5317,
            "runeSlotId": 18
          },
          {
            "runeId": 5295,
            "runeSlotId": 19
          },
          {
            "runeId": 5295,
            "runeSlotId": 20
          },
          {
            "runeId": 5295,
            "runeSlotId": 21
          },
          {
            "runeId": 5295,
            "runeSlotId": 22
          },
          {
            "runeId": 5295,
            "runeSlotId": 23
          },
          {
            "runeId": 5295,
            "runeSlotId": 24
          },
          {
            "runeId": 5295,
            "runeSlotId": 25
          },
          {
            "runeId": 5295,
            "runeSlotId": 26
          },
          {
            "runeId": 5295,
            "runeSlotId": 27
          },
          {
            "runeId": 5335,
            "runeSlotId": 28
          },
          {
            "runeId": 5335,
            "runeSlotId": 29
          },
          {
            "runeId": 5335,
            "runeSlotId": 30
          }
        ],
        "current": false,
        "name": "AD Cdr",
        "id": 31038298
      },
      {
        "slots": [
          {
            "runeId": 5253,
            "runeSlotId": 1
          },
          {
            "runeId": 5253,
            "runeSlotId": 2
          },
          {
            "runeId": 5251,
            "runeSlotId": 3
          },
          {
            "runeId": 5253,
            "runeSlotId": 4
          },
          {
            "runeId": 5253,
            "runeSlotId": 5
          },
          {
            "runeId": 5253,
            "runeSlotId": 6
          },
          {
            "runeId": 5253,
            "runeSlotId": 7
          },
          {
            "runeId": 5253,
            "runeSlotId": 8
          },
          {
            "runeId": 5253,
            "runeSlotId": 9
          },
          {
            "runeId": 5317,
            "runeSlotId": 10
          },
          {
            "runeId": 5317,
            "runeSlotId": 11
          },
          {
            "runeId": 5317,
            "runeSlotId": 12
          },
          {
            "runeId": 5317,
            "runeSlotId": 13
          },
          {
            "runeId": 5317,
            "runeSlotId": 14
          },
          {
            "runeId": 5317,
            "runeSlotId": 15
          },
          {
            "runeId": 5317,
            "runeSlotId": 16
          },
          {
            "runeId": 5317,
            "runeSlotId": 17
          },
          {
            "runeId": 5317,
            "runeSlotId": 18
          },
          {
            "runeId": 5289,
            "runeSlotId": 19
          },
          {
            "runeId": 5289,
            "runeSlotId": 20
          },
          {
            "runeId": 5289,
            "runeSlotId": 21
          },
          {
            "runeId": 5289,
            "runeSlotId": 22
          },
          {
            "runeId": 5289,
            "runeSlotId": 23
          },
          {
            "runeId": 5289,
            "runeSlotId": 24
          },
          {
            "runeId": 5289,
            "runeSlotId": 25
          },
          {
            "runeId": 5289,
            "runeSlotId": 26
          },
          {
            "runeId": 5289,
            "runeSlotId": 27
          },
          {
            "runeId": 5335,
            "runeSlotId": 28
          },
          {
            "runeId": 5335,
            "runeSlotId": 29
          },
          {
            "runeId": 5335,
            "runeSlotId": 30
          }
        ],
        "current": false,
        "name": "ArPen Standard",
        "id": 31038299
      },
      {
        "slots": [
          {
            "runeId": 5251,
            "runeSlotId": 1
          },
          {
            "runeId": 5253,
            "runeSlotId": 2
          },
          {
            "runeId": 5253,
            "runeSlotId": 3
          },
          {
            "runeId": 5253,
            "runeSlotId": 4
          },
          {
            "runeId": 5253,
            "runeSlotId": 5
          },
          {
            "runeId": 5253,
            "runeSlotId": 6
          },
          {
            "runeId": 5253,
            "runeSlotId": 7
          },
          {
            "runeId": 5253,
            "runeSlotId": 8
          },
          {
            "runeId": 5253,
            "runeSlotId": 9
          },
          {
            "runeId": 5317,
            "runeSlotId": 10
          },
          {
            "runeId": 5317,
            "runeSlotId": 11
          },
          {
            "runeId": 5317,
            "runeSlotId": 12
          },
          {
            "runeId": 5317,
            "runeSlotId": 13
          },
          {
            "runeId": 5317,
            "runeSlotId": 14
          },
          {
            "runeId": 5317,
            "runeSlotId": 15
          },
          {
            "runeId": 5317,
            "runeSlotId": 16
          },
          {
            "runeId": 5317,
            "runeSlotId": 17
          },
          {
            "runeId": 5317,
            "runeSlotId": 18
          },
          {
            "runeId": 5295,
            "runeSlotId": 19
          },
          {
            "runeId": 5295,
            "runeSlotId": 20
          },
          {
            "runeId": 5295,
            "runeSlotId": 21
          },
          {
            "runeId": 5295,
            "runeSlotId": 22
          },
          {
            "runeId": 5295,
            "runeSlotId": 23
          },
          {
            "runeId": 5295,
            "runeSlotId": 24
          },
          {
            "runeId": 5295,
            "runeSlotId": 25
          },
          {
            "runeId": 5295,
            "runeSlotId": 26
          },
          {
            "runeId": 5295,
            "runeSlotId": 27
          },
          {
            "runeId": 5335,
            "runeSlotId": 28
          },
          {
            "runeId": 5335,
            "runeSlotId": 29
          },
          {
            "runeId": 5335,
            "runeSlotId": 30
          }
        ],
        "current": false,
        "name": "ArPen Cdr",
        "id": 31038300
      },
      {
        "slots": [
          {
            "runeId": 5402,
            "runeSlotId": 1
          },
          {
            "runeId": 5402,
            "runeSlotId": 2
          },
          {
            "runeId": 5251,
            "runeSlotId": 3
          },
          {
            "runeId": 5402,
            "runeSlotId": 4
          },
          {
            "runeId": 5402,
            "runeSlotId": 5
          },
          {
            "runeId": 5402,
            "runeSlotId": 6
          },
          {
            "runeId": 5402,
            "runeSlotId": 7
          },
          {
            "runeId": 5402,
            "runeSlotId": 8
          },
          {
            "runeId": 5402,
            "runeSlotId": 9
          },
          {
            "runeId": 5317,
            "runeSlotId": 10
          },
          {
            "runeId": 5317,
            "runeSlotId": 11
          },
          {
            "runeId": 5317,
            "runeSlotId": 12
          },
          {
            "runeId": 5317,
            "runeSlotId": 13
          },
          {
            "runeId": 5317,
            "runeSlotId": 14
          },
          {
            "runeId": 5317,
            "runeSlotId": 15
          },
          {
            "runeId": 5317,
            "runeSlotId": 16
          },
          {
            "runeId": 5317,
            "runeSlotId": 17
          },
          {
            "runeId": 5317,
            "runeSlotId": 18
          },
          {
            "runeId": 5289,
            "runeSlotId": 19
          },
          {
            "runeId": 5289,
            "runeSlotId": 20
          },
          {
            "runeId": 5289,
            "runeSlotId": 21
          },
          {
            "runeId": 5289,
            "runeSlotId": 22
          },
          {
            "runeId": 5289,
            "runeSlotId": 23
          },
          {
            "runeId": 5289,
            "runeSlotId": 24
          },
          {
            "runeId": 5289,
            "runeSlotId": 25
          },
          {
            "runeId": 5289,
            "runeSlotId": 26
          },
          {
            "runeId": 5289,
            "runeSlotId": 27
          },
          {
            "runeId": 5352,
            "runeSlotId": 28
          },
          {
            "runeId": 5352,
            "runeSlotId": 29
          },
          {
            "runeId": 5352,
            "runeSlotId": 30
          }
        ],
        "current": false,
        "name": "Mundo",
        "id": 31038301
      },
      {
        "slots": [
          {
            "runeId": 5251,
            "runeSlotId": 1
          },
          {
            "runeId": 5247,
            "runeSlotId": 2
          },
          {
            "runeId": 5247,
            "runeSlotId": 3
          },
          {
            "runeId": 5247,
            "runeSlotId": 4
          },
          {
            "runeId": 5247,
            "runeSlotId": 5
          },
          {
            "runeId": 5247,
            "runeSlotId": 6
          },
          {
            "runeId": 5247,
            "runeSlotId": 7
          },
          {
            "runeId": 5247,
            "runeSlotId": 8
          },
          {
            "runeId": 5247,
            "runeSlotId": 9
          },
          {
            "runeId": 5317,
            "runeSlotId": 10
          },
          {
            "runeId": 5317,
            "runeSlotId": 11
          },
          {
            "runeId": 5317,
            "runeSlotId": 12
          },
          {
            "runeId": 5317,
            "runeSlotId": 13
          },
          {
            "runeId": 5317,
            "runeSlotId": 14
          },
          {
            "runeId": 5317,
            "runeSlotId": 15
          },
          {
            "runeId": 5317,
            "runeSlotId": 16
          },
          {
            "runeId": 5317,
            "runeSlotId": 17
          },
          {
            "runeId": 5317,
            "runeSlotId": 18
          },
          {
            "runeId": 5289,
            "runeSlotId": 19
          },
          {
            "runeId": 5289,
            "runeSlotId": 20
          },
          {
            "runeId": 5289,
            "runeSlotId": 21
          },
          {
            "runeId": 5289,
            "runeSlotId": 22
          },
          {
            "runeId": 5289,
            "runeSlotId": 23
          },
          {
            "runeId": 5289,
            "runeSlotId": 24
          },
          {
            "runeId": 5289,
            "runeSlotId": 25
          },
          {
            "runeId": 5289,
            "runeSlotId": 26
          },
          {
            "runeId": 5289,
            "runeSlotId": 27
          },
          {
            "runeId": 5335,
            "runeSlotId": 28
          },
          {
            "runeId": 5335,
            "runeSlotId": 29
          },
          {
            "runeId": 5335,
            "runeSlotId": 30
          }
        ],
        "current": false,
        "name": "AS Standard AD",
        "id": 31038302
      },
      {
        "slots": [
          {
            "runeId": 5257,
            "runeSlotId": 1
          },
          {
            "runeId": 5257,
            "runeSlotId": 2
          },
          {
            "runeId": 5257,
            "runeSlotId": 3
          },
          {
            "runeId": 5257,
            "runeSlotId": 4
          },
          {
            "runeId": 5257,
            "runeSlotId": 5
          },
          {
            "runeId": 5257,
            "runeSlotId": 6
          },
          {
            "runeId": 5257,
            "runeSlotId": 7
          },
          {
            "runeId": 5257,
            "runeSlotId": 8
          },
          {
            "runeId": 5257,
            "runeSlotId": 9
          },
          {
            "runeId": 5317,
            "runeSlotId": 10
          },
          {
            "runeId": 5317,
            "runeSlotId": 11
          },
          {
            "runeId": 5317,
            "runeSlotId": 12
          },
          {
            "runeId": 5317,
            "runeSlotId": 13
          },
          {
            "runeId": 5317,
            "runeSlotId": 14
          },
          {
            "runeId": 5317,
            "runeSlotId": 15
          },
          {
            "runeId": 5317,
            "runeSlotId": 16
          },
          {
            "runeId": 5317,
            "runeSlotId": 17
          },
          {
            "runeId": 5317,
            "runeSlotId": 18
          },
          {
            "runeId": 5289,
            "runeSlotId": 19
          },
          {
            "runeId": 5289,
            "runeSlotId": 20
          },
          {
            "runeId": 5289,
            "runeSlotId": 21
          },
          {
            "runeId": 5289,
            "runeSlotId": 22
          },
          {
            "runeId": 5289,
            "runeSlotId": 23
          },
          {
            "runeId": 5289,
            "runeSlotId": 24
          },
          {
            "runeId": 5289,
            "runeSlotId": 25
          },
          {
            "runeId": 5289,
            "runeSlotId": 26
          },
          {
            "runeId": 5289,
            "runeSlotId": 27
          },
          {
            "runeId": 5345,
            "runeSlotId": 28
          },
          {
            "runeId": 5345,
            "runeSlotId": 29
          },
          {
            "runeId": 5345,
            "runeSlotId": 30
          }
        ],
        "current": false,
        "name": "Armored Tank",
        "id": 31038303
      },
      {
        "slots": [
          {
            "runeId": 5257,
            "runeSlotId": 1
          },
          {
            "runeId": 5257,
            "runeSlotId": 2
          },
          {
            "runeId": 5257,
            "runeSlotId": 3
          },
          {
            "runeId": 5257,
            "runeSlotId": 4
          },
          {
            "runeId": 5257,
            "runeSlotId": 5
          },
          {
            "runeId": 5257,
            "runeSlotId": 6
          },
          {
            "runeId": 5257,
            "runeSlotId": 7
          },
          {
            "runeId": 5257,
            "runeSlotId": 8
          },
          {
            "runeId": 5257,
            "runeSlotId": 9
          },
          {
            "runeId": 5317,
            "runeSlotId": 10
          },
          {
            "runeId": 5317,
            "runeSlotId": 11
          },
          {
            "runeId": 5317,
            "runeSlotId": 12
          },
          {
            "runeId": 5317,
            "runeSlotId": 13
          },
          {
            "runeId": 5317,
            "runeSlotId": 14
          },
          {
            "runeId": 5317,
            "runeSlotId": 15
          },
          {
            "runeId": 5317,
            "runeSlotId": 16
          },
          {
            "runeId": 5317,
            "runeSlotId": 17
          },
          {
            "runeId": 5317,
            "runeSlotId": 18
          },
          {
            "runeId": 5289,
            "runeSlotId": 19
          },
          {
            "runeId": 5289,
            "runeSlotId": 20
          },
          {
            "runeId": 5289,
            "runeSlotId": 21
          },
          {
            "runeId": 5289,
            "runeSlotId": 22
          },
          {
            "runeId": 5289,
            "runeSlotId": 23
          },
          {
            "runeId": 5289,
            "runeSlotId": 24
          },
          {
            "runeId": 5289,
            "runeSlotId": 25
          },
          {
            "runeId": 5289,
            "runeSlotId": 26
          },
          {
            "runeId": 5289,
            "runeSlotId": 27
          },
          {
            "runeId": 5367,
            "runeSlotId": 28
          },
          {
            "runeId": 5367,
            "runeSlotId": 29
          },
          {
            "runeId": 5367,
            "runeSlotId": 30
          }
        ],
        "current": false,
        "name": "Support Tank",
        "id": 33903058
      },
      {
        "slots": [
          {
            "runeId": 5245,
            "runeSlotId": 1
          },
          {
            "runeId": 5245,
            "runeSlotId": 2
          },
          {
            "runeId": 5245,
            "runeSlotId": 3
          },
          {
            "runeId": 5245,
            "runeSlotId": 4
          },
          {
            "runeId": 5245,
            "runeSlotId": 5
          },
          {
            "runeId": 5245,
            "runeSlotId": 6
          },
          {
            "runeId": 5245,
            "runeSlotId": 7
          },
          {
            "runeId": 5245,
            "runeSlotId": 8
          },
          {
            "runeId": 5251,
            "runeSlotId": 9
          },
          {
            "runeId": 5317,
            "runeSlotId": 10
          },
          {
            "runeId": 5317,
            "runeSlotId": 11
          },
          {
            "runeId": 5317,
            "runeSlotId": 12
          },
          {
            "runeId": 5317,
            "runeSlotId": 13
          },
          {
            "runeId": 5317,
            "runeSlotId": 14
          },
          {
            "runeId": 5317,
            "runeSlotId": 15
          },
          {
            "runeId": 5317,
            "runeSlotId": 16
          },
          {
            "runeId": 5317,
            "runeSlotId": 17
          },
          {
            "runeId": 5317,
            "runeSlotId": 18
          },
          {
            "runeId": 5289,
            "runeSlotId": 19
          },
          {
            "runeId": 5289,
            "runeSlotId": 20
          },
          {
            "runeId": 5289,
            "runeSlotId": 21
          },
          {
            "runeId": 5289,
            "runeSlotId": 22
          },
          {
            "runeId": 5289,
            "runeSlotId": 23
          },
          {
            "runeId": 5289,
            "runeSlotId": 24
          },
          {
            "runeId": 5289,
            "runeSlotId": 25
          },
          {
            "runeId": 5289,
            "runeSlotId": 26
          },
          {
            "runeId": 5289,
            "runeSlotId": 27
          },
          {
            "runeId": 5345,
            "runeSlotId": 28
          },
          {
            "runeId": 5345,
            "runeSlotId": 29
          },
          {
            "runeId": 5345,
            "runeSlotId": 30
          }
        ],
        "current": false,
        "name": "Bully AD",
        "id": 33903059
      },
      {
        "slots": [
          {
            "runeId": 5273,
            "runeSlotId": 1
          },
          {
            "runeId": 5273,
            "runeSlotId": 2
          },
          {
            "runeId": 5273,
            "runeSlotId": 3
          },
          {
            "runeId": 5273,
            "runeSlotId": 4
          },
          {
            "runeId": 5273,
            "runeSlotId": 5
          },
          {
            "runeId": 5273,
            "runeSlotId": 6
          },
          {
            "runeId": 5273,
            "runeSlotId": 7
          },
          {
            "runeId": 5273,
            "runeSlotId": 8
          },
          {
            "runeId": 5273,
            "runeSlotId": 9
          },
          {
            "runeId": 5317,
            "runeSlotId": 10
          },
          {
            "runeId": 5317,
            "runeSlotId": 11
          },
          {
            "runeId": 5317,
            "runeSlotId": 12
          },
          {
            "runeId": 5317,
            "runeSlotId": 13
          },
          {
            "runeId": 5317,
            "runeSlotId": 14
          },
          {
            "runeId": 5317,
            "runeSlotId": 15
          },
          {
            "runeId": 5317,
            "runeSlotId": 16
          },
          {
            "runeId": 5317,
            "runeSlotId": 17
          },
          {
            "runeId": 5317,
            "runeSlotId": 18
          },
          {
            "runeId": 5289,
            "runeSlotId": 19
          },
          {
            "runeId": 5289,
            "runeSlotId": 20
          },
          {
            "runeId": 5289,
            "runeSlotId": 21
          },
          {
            "runeId": 5289,
            "runeSlotId": 22
          },
          {
            "runeId": 5289,
            "runeSlotId": 23
          },
          {
            "runeId": 5289,
            "runeSlotId": 24
          },
          {
            "runeId": 5289,
            "runeSlotId": 25
          },
          {
            "runeId": 5289,
            "runeSlotId": 26
          },
          {
            "runeId": 5289,
            "runeSlotId": 27
          },
          {
            "runeId": 5357,
            "runeSlotId": 28
          },
          {
            "runeId": 5357,
            "runeSlotId": 29
          },
          {
            "runeId": 5357,
            "runeSlotId": 30
          }
        ],
        "current": false,
        "name": "Standard AP",
        "id": 33903060
      },
      {
        "slots": [
          {
            "runeId": 5273,
            "runeSlotId": 1
          },
          {
            "runeId": 5273,
            "runeSlotId": 2
          },
          {
            "runeId": 5273,
            "runeSlotId": 3
          },
          {
            "runeId": 5273,
            "runeSlotId": 4
          },
          {
            "runeId": 5273,
            "runeSlotId": 5
          },
          {
            "runeId": 5273,
            "runeSlotId": 6
          },
          {
            "runeId": 5273,
            "runeSlotId": 7
          },
          {
            "runeId": 5273,
            "runeSlotId": 8
          },
          {
            "runeId": 5273,
            "runeSlotId": 9
          },
          {
            "runeId": 5317,
            "runeSlotId": 10
          },
          {
            "runeId": 5317,
            "runeSlotId": 11
          },
          {
            "runeId": 5317,
            "runeSlotId": 12
          },
          {
            "runeId": 5317,
            "runeSlotId": 13
          },
          {
            "runeId": 5317,
            "runeSlotId": 14
          },
          {
            "runeId": 5317,
            "runeSlotId": 15
          },
          {
            "runeId": 5317,
            "runeSlotId": 16
          },
          {
            "runeId": 5317,
            "runeSlotId": 17
          },
          {
            "runeId": 5317,
            "runeSlotId": 18
          },
          {
            "runeId": 5298,
            "runeSlotId": 19
          },
          {
            "runeId": 5298,
            "runeSlotId": 20
          },
          {
            "runeId": 5298,
            "runeSlotId": 21
          },
          {
            "runeId": 5298,
            "runeSlotId": 22
          },
          {
            "runeId": 5298,
            "runeSlotId": 23
          },
          {
            "runeId": 5298,
            "runeSlotId": 24
          },
          {
            "runeId": 5298,
            "runeSlotId": 25
          },
          {
            "runeId": 5298,
            "runeSlotId": 26
          },
          {
            "runeId": 5298,
            "runeSlotId": 27
          },
          {
            "runeId": 5357,
            "runeSlotId": 28
          },
          {
            "runeId": 5357,
            "runeSlotId": 29
          },
          {
            "runeId": 5357,
            "runeSlotId": 30
          }
        ],
        "current": true,
        "name": "Standard AP w AP\/lvl",
        "id": 33903061
      },
      {
        "slots": [
          {
            "runeId": 5273,
            "runeSlotId": 1
          },
          {
            "runeId": 5273,
            "runeSlotId": 2
          },
          {
            "runeId": 5273,
            "runeSlotId": 3
          },
          {
            "runeId": 5273,
            "runeSlotId": 4
          },
          {
            "runeId": 5273,
            "runeSlotId": 5
          },
          {
            "runeId": 5273,
            "runeSlotId": 6
          },
          {
            "runeId": 5273,
            "runeSlotId": 7
          },
          {
            "runeId": 5273,
            "runeSlotId": 8
          },
          {
            "runeId": 5273,
            "runeSlotId": 9
          },
          {
            "runeId": 5317,
            "runeSlotId": 10
          },
          {
            "runeId": 5317,
            "runeSlotId": 11
          },
          {
            "runeId": 5317,
            "runeSlotId": 12
          },
          {
            "runeId": 5317,
            "runeSlotId": 13
          },
          {
            "runeId": 5317,
            "runeSlotId": 14
          },
          {
            "runeId": 5317,
            "runeSlotId": 15
          },
          {
            "runeId": 5317,
            "runeSlotId": 16
          },
          {
            "runeId": 5317,
            "runeSlotId": 17
          },
          {
            "runeId": 5317,
            "runeSlotId": 18
          },
          {
            "runeId": 5298,
            "runeSlotId": 19
          },
          {
            "runeId": 5298,
            "runeSlotId": 20
          },
          {
            "runeId": 5298,
            "runeSlotId": 21
          },
          {
            "runeId": 5298,
            "runeSlotId": 22
          },
          {
            "runeId": 5298,
            "runeSlotId": 23
          },
          {
            "runeId": 5298,
            "runeSlotId": 24
          },
          {
            "runeId": 5298,
            "runeSlotId": 25
          },
          {
            "runeId": 5298,
            "runeSlotId": 26
          },
          {
            "runeId": 5298,
            "runeSlotId": 27
          },
          {
            "runeId": 5365,
            "runeSlotId": 28
          },
          {
            "runeId": 5365,
            "runeSlotId": 29
          },
          {
            "runeId": 5365,
            "runeSlotId": 30
          }
        ],
        "current": false,
        "name": "Standard AP w MS",
        "id": 33903062
      },
      {
        "slots": [
          {
            "runeId": 5402,
            "runeSlotId": 1
          },
          {
            "runeId": 5402,
            "runeSlotId": 2
          },
          {
            "runeId": 5402,
            "runeSlotId": 3
          },
          {
            "runeId": 5402,
            "runeSlotId": 4
          },
          {
            "runeId": 5402,
            "runeSlotId": 5
          },
          {
            "runeId": 5402,
            "runeSlotId": 6
          },
          {
            "runeId": 5402,
            "runeSlotId": 7
          },
          {
            "runeId": 5402,
            "runeSlotId": 8
          },
          {
            "runeId": 5402,
            "runeSlotId": 9
          },
          {
            "runeId": 5317,
            "runeSlotId": 10
          },
          {
            "runeId": 5317,
            "runeSlotId": 11
          },
          {
            "runeId": 5317,
            "runeSlotId": 12
          },
          {
            "runeId": 5317,
            "runeSlotId": 13
          },
          {
            "runeId": 5317,
            "runeSlotId": 14
          },
          {
            "runeId": 5317,
            "runeSlotId": 15
          },
          {
            "runeId": 5317,
            "runeSlotId": 16
          },
          {
            "runeId": 5317,
            "runeSlotId": 17
          },
          {
            "runeId": 5317,
            "runeSlotId": 18
          },
          {
            "runeId": 5298,
            "runeSlotId": 19
          },
          {
            "runeId": 5298,
            "runeSlotId": 20
          },
          {
            "runeId": 5298,
            "runeSlotId": 21
          },
          {
            "runeId": 5298,
            "runeSlotId": 22
          },
          {
            "runeId": 5298,
            "runeSlotId": 23
          },
          {
            "runeId": 5298,
            "runeSlotId": 24
          },
          {
            "runeId": 5298,
            "runeSlotId": 25
          },
          {
            "runeId": 5298,
            "runeSlotId": 26
          },
          {
            "runeId": 5298,
            "runeSlotId": 27
          },
          {
            "runeId": 5357,
            "runeSlotId": 28
          },
          {
            "runeId": 5357,
            "runeSlotId": 29
          },
          {
            "runeId": 5357,
            "runeSlotId": 30
          }
        ],
        "current": false,
        "name": "Hyb Pen w AP\/lvl",
        "id": 33903063
      },
      {
        "slots": [
          {
            "runeId": 5402,
            "runeSlotId": 1
          },
          {
            "runeId": 5402,
            "runeSlotId": 2
          },
          {
            "runeId": 5402,
            "runeSlotId": 3
          },
          {
            "runeId": 5402,
            "runeSlotId": 4
          },
          {
            "runeId": 5402,
            "runeSlotId": 5
          },
          {
            "runeId": 5402,
            "runeSlotId": 6
          },
          {
            "runeId": 5402,
            "runeSlotId": 7
          },
          {
            "runeId": 5402,
            "runeSlotId": 8
          },
          {
            "runeId": 5402,
            "runeSlotId": 9
          },
          {
            "runeId": 5317,
            "runeSlotId": 10
          },
          {
            "runeId": 5317,
            "runeSlotId": 11
          },
          {
            "runeId": 5317,
            "runeSlotId": 12
          },
          {
            "runeId": 5317,
            "runeSlotId": 13
          },
          {
            "runeId": 5317,
            "runeSlotId": 14
          },
          {
            "runeId": 5317,
            "runeSlotId": 15
          },
          {
            "runeId": 5317,
            "runeSlotId": 16
          },
          {
            "runeId": 5317,
            "runeSlotId": 17
          },
          {
            "runeId": 5317,
            "runeSlotId": 18
          },
          {
            "runeId": 5289,
            "runeSlotId": 19
          },
          {
            "runeId": 5289,
            "runeSlotId": 20
          },
          {
            "runeId": 5289,
            "runeSlotId": 21
          },
          {
            "runeId": 5289,
            "runeSlotId": 22
          },
          {
            "runeId": 5289,
            "runeSlotId": 23
          },
          {
            "runeId": 5289,
            "runeSlotId": 24
          },
          {
            "runeId": 5289,
            "runeSlotId": 25
          },
          {
            "runeId": 5289,
            "runeSlotId": 26
          },
          {
            "runeId": 5289,
            "runeSlotId": 27
          },
          {
            "runeId": 5365,
            "runeSlotId": 28
          },
          {
            "runeId": 5365,
            "runeSlotId": 29
          },
          {
            "runeId": 5365,
            "runeSlotId": 30
          }
        ],
        "current": false,
        "name": "Hyb Pen w MS",
        "id": 33903064
      },
      {
        "slots": [
          {
            "runeId": 5402,
            "runeSlotId": 1
          },
          {
            "runeId": 5402,
            "runeSlotId": 2
          },
          {
            "runeId": 5402,
            "runeSlotId": 3
          },
          {
            "runeId": 5402,
            "runeSlotId": 4
          },
          {
            "runeId": 5402,
            "runeSlotId": 5
          },
          {
            "runeId": 5402,
            "runeSlotId": 6
          },
          {
            "runeId": 5402,
            "runeSlotId": 7
          },
          {
            "runeId": 5402,
            "runeSlotId": 8
          },
          {
            "runeId": 5402,
            "runeSlotId": 9
          },
          {
            "runeId": 5317,
            "runeSlotId": 10
          },
          {
            "runeId": 5317,
            "runeSlotId": 11
          },
          {
            "runeId": 5317,
            "runeSlotId": 12
          },
          {
            "runeId": 5317,
            "runeSlotId": 13
          },
          {
            "runeId": 5317,
            "runeSlotId": 14
          },
          {
            "runeId": 5317,
            "runeSlotId": 15
          },
          {
            "runeId": 5317,
            "runeSlotId": 16
          },
          {
            "runeId": 5317,
            "runeSlotId": 17
          },
          {
            "runeId": 5317,
            "runeSlotId": 18
          },
          {
            "runeId": 5298,
            "runeSlotId": 19
          },
          {
            "runeId": 5298,
            "runeSlotId": 20
          },
          {
            "runeId": 5298,
            "runeSlotId": 21
          },
          {
            "runeId": 5298,
            "runeSlotId": 22
          },
          {
            "runeId": 5298,
            "runeSlotId": 23
          },
          {
            "runeId": 5298,
            "runeSlotId": 24
          },
          {
            "runeId": 5298,
            "runeSlotId": 25
          },
          {
            "runeId": 5298,
            "runeSlotId": 26
          },
          {
            "runeId": 5298,
            "runeSlotId": 27
          },
          {
            "runeId": 5365,
            "runeSlotId": 28
          },
          {
            "runeId": 5365,
            "runeSlotId": 29
          },
          {
            "runeId": 5365,
            "runeSlotId": 30
          }
        ],
        "current": false,
        "name": "Hyb Pen MS & AP\/lvl",
        "id": 44504963
      },
      {
        "slots": [
          {
            "runeId": 5247,
            "runeSlotId": 1
          },
          {
            "runeId": 5247,
            "runeSlotId": 2
          },
          {
            "runeId": 5247,
            "runeSlotId": 3
          },
          {
            "runeId": 5247,
            "runeSlotId": 4
          },
          {
            "runeId": 5247,
            "runeSlotId": 5
          },
          {
            "runeId": 5247,
            "runeSlotId": 6
          },
          {
            "runeId": 5247,
            "runeSlotId": 7
          },
          {
            "runeId": 5247,
            "runeSlotId": 8
          },
          {
            "runeId": 5251,
            "runeSlotId": 9
          },
          {
            "runeId": 5317,
            "runeSlotId": 10
          },
          {
            "runeId": 5317,
            "runeSlotId": 11
          },
          {
            "runeId": 5317,
            "runeSlotId": 12
          },
          {
            "runeId": 5317,
            "runeSlotId": 13
          },
          {
            "runeId": 5317,
            "runeSlotId": 14
          },
          {
            "runeId": 5317,
            "runeSlotId": 15
          },
          {
            "runeId": 5317,
            "runeSlotId": 16
          },
          {
            "runeId": 5317,
            "runeSlotId": 17
          },
          {
            "runeId": 5317,
            "runeSlotId": 18
          },
          {
            "runeId": 5289,
            "runeSlotId": 19
          },
          {
            "runeId": 5289,
            "runeSlotId": 20
          },
          {
            "runeId": 5289,
            "runeSlotId": 21
          },
          {
            "runeId": 5289,
            "runeSlotId": 22
          },
          {
            "runeId": 5289,
            "runeSlotId": 23
          },
          {
            "runeId": 5289,
            "runeSlotId": 24
          },
          {
            "runeId": 5289,
            "runeSlotId": 25
          },
          {
            "runeId": 5289,
            "runeSlotId": 26
          },
          {
            "runeId": 5289,
            "runeSlotId": 27
          },
          {
            "runeId": 5357,
            "runeSlotId": 28
          },
          {
            "runeId": 5357,
            "runeSlotId": 29
          },
          {
            "runeId": 5357,
            "runeSlotId": 30
          }
        ],
        "current": false,
        "name": "AP w AS",
        "id": 47524699
      },
      {
        "slots": [
          {
            "runeId": 5247,
            "runeSlotId": 1
          },
          {
            "runeId": 5247,
            "runeSlotId": 2
          },
          {
            "runeId": 5251,
            "runeSlotId": 3
          },
          {
            "runeId": 5247,
            "runeSlotId": 4
          },
          {
            "runeId": 5247,
            "runeSlotId": 5
          },
          {
            "runeId": 5247,
            "runeSlotId": 6
          },
          {
            "runeId": 5247,
            "runeSlotId": 7
          },
          {
            "runeId": 5247,
            "runeSlotId": 8
          },
          {
            "runeId": 5247,
            "runeSlotId": 9
          },
          {
            "runeId": 5317,
            "runeSlotId": 10
          },
          {
            "runeId": 5317,
            "runeSlotId": 11
          },
          {
            "runeId": 5317,
            "runeSlotId": 12
          },
          {
            "runeId": 5317,
            "runeSlotId": 13
          },
          {
            "runeId": 5317,
            "runeSlotId": 14
          },
          {
            "runeId": 5317,
            "runeSlotId": 15
          },
          {
            "runeId": 5317,
            "runeSlotId": 16
          },
          {
            "runeId": 5317,
            "runeSlotId": 17
          },
          {
            "runeId": 5317,
            "runeSlotId": 18
          },
          {
            "runeId": 5295,
            "runeSlotId": 19
          },
          {
            "runeId": 5295,
            "runeSlotId": 20
          },
          {
            "runeId": 5295,
            "runeSlotId": 21
          },
          {
            "runeId": 5295,
            "runeSlotId": 22
          },
          {
            "runeId": 5295,
            "runeSlotId": 23
          },
          {
            "runeId": 5295,
            "runeSlotId": 24
          },
          {
            "runeId": 5295,
            "runeSlotId": 25
          },
          {
            "runeId": 5295,
            "runeSlotId": 26
          },
          {
            "runeId": 5295,
            "runeSlotId": 27
          },
          {
            "runeId": 5412,
            "runeSlotId": 28
          },
          {
            "runeId": 5365,
            "runeSlotId": 29
          },
          {
            "runeId": 5365,
            "runeSlotId": 30
          }
        ],
        "current": false,
        "name": "Udyr",
        "id": 47524700
      },
      {
        "slots": [
          {
            "runeId": 5245,
            "runeSlotId": 1
          },
          {
            "runeId": 5245,
            "runeSlotId": 2
          },
          {
            "runeId": 5245,
            "runeSlotId": 3
          },
          {
            "runeId": 5245,
            "runeSlotId": 4
          },
          {
            "runeId": 5245,
            "runeSlotId": 5
          },
          {
            "runeId": 5245,
            "runeSlotId": 6
          },
          {
            "runeId": 5245,
            "runeSlotId": 7
          },
          {
            "runeId": 5245,
            "runeSlotId": 8
          },
          {
            "runeId": 5245,
            "runeSlotId": 9
          },
          {
            "runeId": 5317,
            "runeSlotId": 10
          },
          {
            "runeId": 5317,
            "runeSlotId": 11
          },
          {
            "runeId": 5317,
            "runeSlotId": 12
          },
          {
            "runeId": 5317,
            "runeSlotId": 13
          },
          {
            "runeId": 5317,
            "runeSlotId": 14
          },
          {
            "runeId": 5317,
            "runeSlotId": 15
          },
          {
            "runeId": 5317,
            "runeSlotId": 16
          },
          {
            "runeId": 5317,
            "runeSlotId": 17
          },
          {
            "runeId": 5317,
            "runeSlotId": 18
          },
          {
            "runeId": 5297,
            "runeSlotId": 19
          },
          {
            "runeId": 5297,
            "runeSlotId": 20
          },
          {
            "runeId": 5297,
            "runeSlotId": 21
          },
          {
            "runeId": 5297,
            "runeSlotId": 22
          },
          {
            "runeId": 5297,
            "runeSlotId": 23
          },
          {
            "runeId": 5297,
            "runeSlotId": 24
          },
          {
            "runeId": 5297,
            "runeSlotId": 25
          },
          {
            "runeId": 5297,
            "runeSlotId": 26
          },
          {
            "runeId": 5297,
            "runeSlotId": 27
          },
          {
            "runeId": 5357,
            "runeSlotId": 28
          },
          {
            "runeId": 5357,
            "runeSlotId": 29
          },
          {
            "runeId": 5357,
            "runeSlotId": 30
          }
        ],
        "current": false,
        "name": "Evelynn",
        "id": 62085547
      }
    ],
    "summonerId": 30743211
  }
}
